[
{ "name": "hello", "trans": ["喂；你好（表示问候）"] },
{ "name": "hi", "trans": ["嗨；你好（非正式用语，=hello）"] },
{ "name": "boy", "trans": ["男孩"] },
{ "name": "girl", "trans": ["女孩"] },
{ "name": "teacher", "trans": ["教师"] },
{ "name": "school", "trans": ["（中、小）学校；上学"] },
{ "name": "book", "trans": ["书"] },
{ "name": "chair", "trans": ["椅子"] },
{ "name": "desk", "trans": ["书桌"] },
{ "name": "one", "trans": ["一"] },
{ "name": "two", "trans": ["二"] },
{ "name": "three", "trans": ["三"] },
{ "name": "four", "trans": ["四"] },
{ "name": "five", "trans": ["五"] },
{ "name": "pencil", "trans": ["铅笔"] },
{ "name": "pen", "trans": ["钢笔"] },
{ "name": "ruler", "trans": ["直尺"] },
{ "name": "crayon", "trans": ["彩色蜡笔（或粉笔、铅笔）"] },
{ "name": "pencil box", "trans": ["铅笔盒"] },
{ "name": "six", "trans": ["六"] },
{ "name": "seven", "trans": ["七"] },
{ "name": "eight", "trans": ["八"] },
{ "name": "nine", "trans": ["九"] },
{ "name": "ten", "trans": ["十"] },
{ "name": "friend", "trans": ["朋友"] },
{ "name": "window", "trans": ["窗户"] },
{ "name": "red", "trans": ["红色；红色的"] },
{ "name": "yellow", "trans": ["黄色；黄色的"] },
{ "name": "blue", "trans": ["蓝色；蓝色的"] },
{ "name": "green", "trans": ["绿色；绿色的"] },
{ "name": "orange", "trans": ["橙；橘黄色；橘黄色的"] },
{ "name": "brown", "trans": ["棕色；棕色的"] },
{ "name": "white", "trans": ["白色；白色的"] },
{ "name": "black", "trans": ["黑色；黑色的"] },
{ "name": "cold", "trans": ["冷的"] },
{ "name": "hot", "trans": ["热的"] },
{ "name": "tired", "trans": ["疲劳的；累的"] },
{ "name": "happy", "trans": ["高兴地；幸福的"] },
{ "name": "sad", "trans": ["悲伤的"] },
{ "name": "body", "trans": ["身体"] },
{ "name": "hand", "trans": ["手"] },
{ "name": "head", "trans": ["头"] },
{ "name": "arm", "trans": ["胳膊"] },
{ "name": "leg", "trans": ["腿"] },
{ "name": "foot", "trans": ["脚（复数为feet）"] },
{ "name": "left", "trans": ["左边；左边的"] },
{ "name": "right", "trans": ["右边；右边的"] },
{ "name": "hair", "trans": ["头发"] },
{ "name": "eye", "trans": ["眼睛"] },
{ "name": "mouth", "trans": ["嘴"] },
{ "name": "ear", "trans": ["耳朵"] },
{ "name": "nose", "trans": ["鼻子"] },
{ "name": "face", "trans": ["脸；面"] },
{ "name": "warm", "trans": ["暖和的；温暖的"] },
{ "name": "cool", "trans": ["凉爽的；绝妙的，酷的"] },
{ "name": "doctor", "trans": ["医生（缩写形式为Dr.）"] },
{ "name": "family", "trans": ["家庭；一家人"] },
{ "name": "father", "trans": ["父亲"] },
{ "name": "mother", "trans": ["母亲"] },
{ "name": "brother", "trans": ["兄；弟"] },
{ "name": "sister", "trans": ["姐；妹"] },
{ "name": "China", "trans": ["中国"] },
{ "name": "short", "trans": ["矮的；短的"] },
{ "name": "tall", "trans": ["高的"] },
{ "name": "policeman", "trans": ["男警察"] },
{ "name": "bus", "trans": ["公共汽车"] },
{ "name": "driver", "trans": ["司机"] },
{ "name": "worker", "trans": ["工人"] },
{ "name": "old", "trans": ["年老的；…岁的"] },
{ "name": "young", "trans": ["年轻的"] },
{ "name": "birthday", "trans": ["生日"] },
{ "name": "party", "trans": ["聚会；宴会"] },
{ "name": "cake", "trans": ["蛋糕"] }
]